{
  "model": "User",
  "fields": {
    "id": {"type": "int", "not_null": "true", "primary": "true", "autoincrement": "true"},
    "username": {"type": "string", "not_null": "true", "required": "true", "maxLength": "50"},
    "email": {"type": "string", "not_null": "true", "required": "true", "maxLength": "255"},
    "password_hash": {"type": "string", "not_null": "true", "required": "true", "maxLength": "255"},
    "display_name": {"type": "string", "maxLength": "100"},
    "bio": {"type": "string"},
    "is_active": {"type": "bool", "not_null": "true", "required": "true"},
    "created_at": {"type": "datetime", "not_null": "true"},
    "updated_at": {"type": "datetime", "not_null": "true"}
  }
  ,
  "joins": {
    "details": {
      "model": "UserData",
      "joinsOn": "users.id",
      "fields": {"$ref": "userdetails.model.json"}
    }
  }
}
